voter_if.v
module voter_if (I, O);
input [3:0] I; // I 4 men
output [3:1] O; // O Result
reg [3:1] O; //4bit 暫存器

always@ (I)
case (I)    // 當反對人數大於贊成人數O[3]=1，反之O[3]=0
    4'b0000 :
        O[3] = 1;
    4'b0001 :
        O[3] = 1;
    4'b0010 :
        O[3] = 1;
    4'b0100 :
        O[3] = 1;
    4'b1000 :
        O[3] = 1;
    default :
        O[3] = 0;
endcase

always@ (I)
case (I)   // 當反對人數等於贊成人數O[2]=1，反之O[2]=0
    4'b0011 :
        O[2] = 1;
    4'b0110 :
        O[2] = 1;
    4'b1100 :
        O[2] = 1;
    4'b1001 :
        O[2] = 1;
    4'b1010 :
        O[2] = 1;
    4'b0101 :
        O[2] = 1;
    default :
        O[2] = 0;
endcase

always@ (I)
case (I)   // 當反對人數小於贊成人數O[1]=1，反之O[1]=0
    4'b1110 :
        O[1] = 1;
    4'b1101 :
        O[1] = 1;
    4'b1011 :
        O[1] = 1;
    4'b0111 :
        O[1] = 1;
    4'b1111 :
        O[1] = 1;
    default :
        O[1] = 0;
endcase

endmodule

Testbench.v
`timescale 1ns/1ps
module Testbench;
reg [3:0] I = 4'b0000;  //4bit 暫存器
wire [3:1] O = 4'b000;   //3bit 暫存器

voter_if UUT (.I(I),.O(O));      //用變數UTT來接收輸入和輸出
initial
begin       //將輸入的所有可能，按時間一一輸入
    #50 I = 4'b0000;
    #50 I = 4'b0001;
    #50 I = 4'b0010;
    #50 I = 4'b0011;
    #50 I = 4'b0100;
    #50 I = 4'b0101;
    #50 I = 4'b0110;
    #50 I = 4'b0111;
    #50 I = 4'b1000;
    #50 I = 4'b1001;
    #50 I = 4'b1010;
    #50 I = 4'b1011;
    #50 I = 4'b1100;
    #50 I = 4'b1101;
    #50 I = 4'b1110;
    #50 I = 4'b1111;
    #50 $finish;
end

initial
begin
    $dumpfile("simple.vcd");    //將指定資訊匯入 VCD 檔案
    $dumpvars(0, UUT);          //紀錄UTT變數接收的所有信號
end
endmodule

simple.vcd
$date
	Sun Apr 17 02:36:23 2022
$end
$version
	Icarus Verilog
$end
$timescale
	1ps
$end
$scope module Testbench $end
$scope module UUT $end
$var wire 4 ! I [3:0] $end
$var reg 3 " O [3:1] $end
$upscope $end
$upscope $end
$enddefinitions $end
#0
$dumpvars
b100 "
b0 !
$end
#100000
b1 !
#150000
b10 !
#200000
b10 "
b11 !
#250000
b100 "
b100 !
#300000
b10 "
b101 !
#350000
b110 !
#400000
b1 "
b111 !
#450000
b100 "
b1000 !
#500000
b10 "
b1001 !
#550000
b1010 !
#600000
b1 "
b1011 !
#650000
b10 "
b1100 !
#700000
b1 "
b1101 !
#750000
b1110 !
#800000
b1111 !
